{"format":1,"version":"4.5.3","settings":"ea59a7a9bb750273967833589050d7a3","files":{"apps_DBmanager_py":{"hash":"39b5ed6c2ad9c300d313f5e3b7ca545a","index":{"nums":[1,82,0,13,0,0,0],"html_filename":"apps_DBmanager_py.html","relative_filename":"apps\\DBmanager.py"}},"apps_DBtest_py":{"hash":"a4f4e66b883c268c7b792ff4ec54301a","index":{"nums":[1,83,0,0,0,0,0],"html_filename":"apps_DBtest_py.html","relative_filename":"apps\\DBtest.py"}},"apps_GestionDatos___init___py":{"hash":"4911cff48f6b9e153df4c1a3ecaded19","index":{"nums":[1,0,0,0,0,0,0],"html_filename":"apps_GestionDatos___init___py.html","relative_filename":"apps\\GestionDatos\\__init__.py"}},"apps_GestionDatos_admin_py":{"hash":"408eb683d93d9c7ac98ab71c5a5eaa61","index":{"nums":[1,3,0,3,0,0,0],"html_filename":"apps_GestionDatos_admin_py.html","relative_filename":"apps\\GestionDatos\\admin.py"}},"apps_GestionDatos_migrations_0001_initial_py":{"hash":"09359abcbe8a9e90b0d4aa69f8a20c18","index":{"nums":[1,6,0,0,0,0,0],"html_filename":"apps_GestionDatos_migrations_0001_initial_py.html","relative_filename":"apps\\GestionDatos\\migrations\\0001_initial.py"}},"apps_GestionDatos_migrations___init___py":{"hash":"182b2dca469bf063cbcf996d517b03da","index":{"nums":[1,0,0,0,0,0,0],"html_filename":"apps_GestionDatos_migrations___init___py.html","relative_filename":"apps\\GestionDatos\\migrations\\__init__.py"}},"apps_GestionDatos_models_py":{"hash":"e79d4a877e3c40dac826a7050202b9b1","index":{"nums":[1,12,0,12,0,0,0],"html_filename":"apps_GestionDatos_models_py.html","relative_filename":"apps\\GestionDatos\\models.py"}},"apps_GestionPlantas___init___py":{"hash":"4911cff48f6b9e153df4c1a3ecaded19","index":{"nums":[1,0,0,0,0,0,0],"html_filename":"apps_GestionPlantas___init___py.html","relative_filename":"apps\\GestionPlantas\\__init__.py"}},"apps_GestionPlantas_admin_py":{"hash":"fd0720b5d8757ad4aaad9c874e7e66f9","index":{"nums":[1,3,0,3,0,0,0],"html_filename":"apps_GestionPlantas_admin_py.html","relative_filename":"apps\\GestionPlantas\\admin.py"}},"apps_GestionPlantas_migrations_0001_initial_py":{"hash":"cd92cbba1b7075b8d169f91524074880","index":{"nums":[1,7,0,0,0,0,0],"html_filename":"apps_GestionPlantas_migrations_0001_initial_py.html","relative_filename":"apps\\GestionPlantas\\migrations\\0001_initial.py"}},"apps_GestionPlantas_migrations___init___py":{"hash":"182b2dca469bf063cbcf996d517b03da","index":{"nums":[1,0,0,0,0,0,0],"html_filename":"apps_GestionPlantas_migrations___init___py.html","relative_filename":"apps\\GestionPlantas\\migrations\\__init__.py"}},"apps_GestionPlantas_models_py":{"hash":"6c5891148145cdf492dbd6635fb9583d","index":{"nums":[1,11,0,9,0,0,0],"html_filename":"apps_GestionPlantas_models_py.html","relative_filename":"apps\\GestionPlantas\\models.py"}},"apps_GestionUsuarios___init___py":{"hash":"4911cff48f6b9e153df4c1a3ecaded19","index":{"nums":[1,0,0,0,0,0,0],"html_filename":"apps_GestionUsuarios___init___py.html","relative_filename":"apps\\GestionUsuarios\\__init__.py"}},"apps_GestionUsuarios_admin_py":{"hash":"327a845cf017881e52d4f3ac73a31eb7","index":{"nums":[1,3,0,3,0,0,0],"html_filename":"apps_GestionUsuarios_admin_py.html","relative_filename":"apps\\GestionUsuarios\\admin.py"}},"apps_GestionUsuarios_migrations_0001_initial_py":{"hash":"4d1cceb7700f0d45f8f1524572ff2368","index":{"nums":[1,5,0,0,0,0,0],"html_filename":"apps_GestionUsuarios_migrations_0001_initial_py.html","relative_filename":"apps\\GestionUsuarios\\migrations\\0001_initial.py"}},"apps_GestionUsuarios_migrations___init___py":{"hash":"182b2dca469bf063cbcf996d517b03da","index":{"nums":[1,0,0,0,0,0,0],"html_filename":"apps_GestionUsuarios_migrations___init___py.html","relative_filename":"apps\\GestionUsuarios\\migrations\\__init__.py"}},"apps_GestionUsuarios_models_py":{"hash":"dd0058cea6fb3f7c21de7fb8283625af","index":{"nums":[1,8,0,7,0,0,0],"html_filename":"apps_GestionUsuarios_models_py.html","relative_filename":"apps\\GestionUsuarios\\models.py"}},"apps___init___py":{"hash":"4911cff48f6b9e153df4c1a3ecaded19","index":{"nums":[1,0,0,0,0,0,0],"html_filename":"apps___init___py.html","relative_filename":"apps\\__init__.py"}},"apps_TiposPlantas___init___py":{"hash":"4911cff48f6b9e153df4c1a3ecaded19","index":{"nums":[1,0,0,0,0,0,0],"html_filename":"apps_TiposPlantas___init___py.html","relative_filename":"apps\\TiposPlantas\\__init__.py"}},"apps_TiposPlantas_admin_py":{"hash":"61e1e043f7dc4422045e117cb69a6df0","index":{"nums":[1,3,0,3,0,0,0],"html_filename":"apps_TiposPlantas_admin_py.html","relative_filename":"apps\\TiposPlantas\\admin.py"}},"apps_TiposPlantas_migrations_0001_initial_py":{"hash":"b14aff756102c476939684dd33c3abaa","index":{"nums":[1,5,0,0,0,0,0],"html_filename":"apps_TiposPlantas_migrations_0001_initial_py.html","relative_filename":"apps\\TiposPlantas\\migrations\\0001_initial.py"}},"apps_TiposPlantas_migrations___init___py":{"hash":"182b2dca469bf063cbcf996d517b03da","index":{"nums":[1,0,0,0,0,0,0],"html_filename":"apps_TiposPlantas_migrations___init___py.html","relative_filename":"apps\\TiposPlantas\\migrations\\__init__.py"}},"apps_TiposPlantas_models_py":{"hash":"d84fa39929dbceceb2c8f07f255a3705","index":{"nums":[1,11,0,10,0,0,0],"html_filename":"apps_TiposPlantas_models_py.html","relative_filename":"apps\\TiposPlantas\\models.py"}},"apps_usuario___init___py":{"hash":"4911cff48f6b9e153df4c1a3ecaded19","index":{"nums":[1,0,0,0,0,0,0],"html_filename":"apps_usuario___init___py.html","relative_filename":"apps\\usuario\\__init__.py"}},"apps_usuario_admin_py":{"hash":"3e2c704cc912f7ad02c4f8e614b143db","index":{"nums":[1,1,0,1,0,0,0],"html_filename":"apps_usuario_admin_py.html","relative_filename":"apps\\usuario\\admin.py"}},"apps_usuario_migrations___init___py":{"hash":"182b2dca469bf063cbcf996d517b03da","index":{"nums":[1,0,0,0,0,0,0],"html_filename":"apps_usuario_migrations___init___py.html","relative_filename":"apps\\usuario\\migrations\\__init__.py"}},"apps_usuario_models_py":{"hash":"b696a9b603f723af6167f4645d325a86","index":{"nums":[1,1,0,1,0,0,0],"html_filename":"apps_usuario_models_py.html","relative_filename":"apps\\usuario\\models.py"}}}}